{
    "version": "1.2.1.0",
    "description": "(Scoop bucket by arch3rpro) DudeSuite - Dude Suite Web Security Tools 单兵作战渗透测试工具",
    "homepage": "https://github.com/x364e3ab6/DudeSuite",
    "license": "Unkown",
    "url": "https://github.com/x364e3ab6/DudeSuite/releases/download/v1.2.1.0/DudeSuite.v1.2.1.0.win-x64.zip",
    "hash": "ff00f4f2d05789792f398aacc75e8de241850774fbd7551f8f81f75ef5d792ae",
    "bin": "DudeSuite.exe",
    "checkver": "github",
    "autoupdate": {
        "url": "https://github.com/x364e3ab6/DudeSuite/releases/download/v1.2.1.0/DudeSuite.v1.2.1.0.win-x64.zip"
    }
}
